aws_cfn_ses_domain/__about__.py
aws_cfn_ses_domain/__init__.py
aws_cfn_ses_domain/cfnresponse.py
aws_cfn_ses_domain/ses_domain_identity.py
aws_cfn_ses_domain/ses_email_identity.py
aws_cfn_ses_domain/utils.py
aws_cfn_ses_domain-0.4.dist-info/LICENSE
aws_cfn_ses_domain-0.4.dist-info/METADATA
aws_cfn_ses_domain-0.4.dist-info/WHEEL
aws_cfn_ses_domain-0.4.dist-info/top_level.txt
aws_cfn_ses_domain-0.4.dist-info/RECORD
