Metadata-Version: 2.1
Name: aws-cfn-ses-domain
Version: 0.4
Summary: AWS CloudFormation resources for Amazon SES domain and email identities
Home-page: https://github.com/medmunds/aws-cfn-ses-domain
Author: Mike Edmunds
Author-email: medmunds@gmail.com
License: Apache License 2.0
Keywords: AWS-CloudFormation CloudFormation CloudFormation-custom-resource CustomResource Amazon-SES SES Route53 AWS-Lambda-Function
Platform: UNKNOWN
Classifier: Development Status :: 4 - Beta
Classifier: Intended Audience :: Developers
Classifier: License :: OSI Approved :: Apache Software License
Classifier: Topic :: System :: Installation/Setup
Classifier: Topic :: System :: Systems Administration
Classifier: Programming Language :: Python :: 3
Classifier: Programming Language :: Python :: 3.9
Requires-Python: >=3.9.0
License-File: LICENSE
Provides-Extra: test
Requires-Dist: boto3 ; extra == 'test'
